getorcreateplus.py
django_getorcreateplus-0.1.0.dist-info/DESCRIPTION.rst
django_getorcreateplus-0.1.0.dist-info/METADATA
django_getorcreateplus-0.1.0.dist-info/RECORD
django_getorcreateplus-0.1.0.dist-info/WHEEL
django_getorcreateplus-0.1.0.dist-info/metadata.json
django_getorcreateplus-0.1.0.dist-info/top_level.txt
