Metadata-Version: 2.0
Name: django-getorcreateplus
Version: 0.1.0
Summary: Mixins to cache, force and/or use non-atomic Model.objects.get_or_create() calls.
Home-page: https://github.com/f0r4y312/django-getorcreateplus
Author: Vimal Aravindashan
Author-email: vimal.aravindashan@gmail.com
License: Apache-2.0
Keywords: django get_or_create update_or_create get create update cache atomic non-atomic
Platform: any
Classifier: Environment :: Web Environment
Classifier: Framework :: Django
Classifier: Framework :: Django :: 1.8
Classifier: Intended Audience :: Developers
Classifier: License :: OSI Approved :: Apache Software License
Classifier: Operating System :: OS Independent
Classifier: Programming Language :: Python
Classifier: Programming Language :: Python :: 2
Classifier: Programming Language :: Python :: 2.7
Classifier: Topic :: Internet :: WWW/HTTP
Classifier: Topic :: Internet :: WWW/HTTP :: Dynamic Content
Requires-Dist: django (>=1.8,<2)
